{
  "schema": "bloodmoon.knowledge.equipment-item.v1",
  "id": "short-sword-silver-heart-short-sword",
  "slug": "silver-heart-short-sword",
  "name": "Silver Heart Short Sword",
  "title": "Silver Heart Short Sword",
  "category": "Short Sword",
  "categorySlug": "short-sword",
  "usableBy": [],
  "listStats": {
    "normalDrop": "~",
    "excellentDrop": "~",
    "attackSpeed": "45"
  },
  "image": {
    "publicPath": "/images/game-assets/guiamuonline/items/original/short-sword-silver-heart-short-sword.jpg",
    "sourceUrl": "https://www.guiamuonline.com/imagenes/items/shortsword/silverheartshort.jpg",
    "localPath": "apps/web/public/images/game-assets/guiamuonline/items/original/short-sword-silver-heart-short-sword.jpg",
    "size": 1112,
    "sha1": "a976741c3a9728e2573f945741305e34bf8a2c5c"
  },
  "source": {
    "normalizedIndex": "apps/web/data/muEquipmentIndex.generated.json",
    "detailFile": "apps/web/data/mu-equipment-details/short-sword.json",
    "sourceUrl": "https://www.guiamuonline.com/spanish/items/shortsword/silverheartshort.html",
    "imageSourceUrl": "https://www.guiamuonline.com/imagenes/items/shortsword/silverheartshort.jpg"
  },
  "statsByLevel": [
    {
      "itemLevel": 0,
      "defense": null,
      "durability": null,
      "damageMin": null,
      "damageMax": null,
      "requiredStrength": null,
      "requiredAgility": null,
      "excellentDefense": null,
      "excellentRequiredStrength": 644,
      "excellentRequiredAgility": 341
    },
    {
      "itemLevel": 1,
      "defense": null,
      "durability": null,
      "damageMin": null,
      "damageMax": null,
      "requiredStrength": null,
      "requiredAgility": null,
      "excellentDefense": null,
      "excellentRequiredStrength": 647,
      "excellentRequiredAgility": 345
    },
    {
      "itemLevel": 2,
      "defense": null,
      "durability": null,
      "damageMin": null,
      "damageMax": null,
      "requiredStrength": null,
      "requiredAgility": null,
      "excellentDefense": null,
      "excellentRequiredStrength": 650,
      "excellentRequiredAgility": 349
    },
    {
      "itemLevel": 3,
      "defense": null,
      "durability": null,
      "damageMin": null,
      "damageMax": null,
      "requiredStrength": null,
      "requiredAgility": null,
      "excellentDefense": null,
      "excellentRequiredStrength": 653,
      "excellentRequiredAgility": 352
    },
    {
      "itemLevel": 4,
      "defense": null,
      "durability": null,
      "damageMin": null,
      "damageMax": null,
      "requiredStrength": null,
      "requiredAgility": null,
      "excellentDefense": null,
      "excellentRequiredStrength": 656,
      "excellentRequiredAgility": 356
    },
    {
      "itemLevel": 5,
      "defense": null,
      "durability": null,
      "damageMin": null,
      "damageMax": null,
      "requiredStrength": null,
      "requiredAgility": null,
      "excellentDefense": null,
      "excellentRequiredStrength": 659,
      "excellentRequiredAgility": 360
    },
    {
      "itemLevel": 6,
      "defense": null,
      "durability": null,
      "damageMin": null,
      "damageMax": null,
      "requiredStrength": null,
      "requiredAgility": null,
      "excellentDefense": null,
      "excellentRequiredStrength": 662,
      "excellentRequiredAgility": 364
    },
    {
      "itemLevel": 7,
      "defense": null,
      "durability": null,
      "damageMin": null,
      "damageMax": null,
      "requiredStrength": null,
      "requiredAgility": null,
      "excellentDefense": null,
      "excellentRequiredStrength": 665,
      "excellentRequiredAgility": 368
    },
    {
      "itemLevel": 8,
      "defense": null,
      "durability": null,
      "damageMin": null,
      "damageMax": null,
      "requiredStrength": null,
      "requiredAgility": null,
      "excellentDefense": null,
      "excellentRequiredStrength": 668,
      "excellentRequiredAgility": 372
    },
    {
      "itemLevel": 9,
      "defense": null,
      "durability": null,
      "damageMin": null,
      "damageMax": null,
      "requiredStrength": null,
      "requiredAgility": null,
      "excellentDefense": null,
      "excellentRequiredStrength": 671,
      "excellentRequiredAgility": 376
    },
    {
      "itemLevel": 10,
      "defense": null,
      "durability": null,
      "damageMin": null,
      "damageMax": null,
      "requiredStrength": null,
      "requiredAgility": null,
      "excellentDefense": null,
      "excellentRequiredStrength": 675,
      "excellentRequiredAgility": 380
    },
    {
      "itemLevel": 11,
      "defense": null,
      "durability": null,
      "damageMin": null,
      "damageMax": null,
      "requiredStrength": null,
      "requiredAgility": null,
      "excellentDefense": null,
      "excellentRequiredStrength": 680,
      "excellentRequiredAgility": 384
    },
    {
      "itemLevel": 12,
      "defense": null,
      "durability": null,
      "damageMin": null,
      "damageMax": null,
      "requiredStrength": null,
      "requiredAgility": null,
      "excellentDefense": null,
      "excellentRequiredStrength": 686,
      "excellentRequiredAgility": 388
    },
    {
      "itemLevel": 13,
      "defense": null,
      "durability": null,
      "damageMin": null,
      "damageMax": null,
      "requiredStrength": null,
      "requiredAgility": null,
      "excellentDefense": null,
      "excellentRequiredStrength": 693,
      "excellentRequiredAgility": 391
    },
    {
      "itemLevel": 14,
      "defense": null,
      "durability": null,
      "damageMin": null,
      "damageMax": null,
      "requiredStrength": null,
      "requiredAgility": null,
      "excellentDefense": null,
      "excellentRequiredStrength": 701,
      "excellentRequiredAgility": 395
    },
    {
      "itemLevel": 15,
      "defense": null,
      "durability": null,
      "damageMin": null,
      "damageMax": null,
      "requiredStrength": null,
      "requiredAgility": null,
      "excellentDefense": null,
      "excellentRequiredStrength": 710,
      "excellentRequiredAgility": 399
    }
  ],
  "parts": [],
  "detailParts": [],
  "editorial": {
    "status": "cataloged-from-normalized-source",
    "reviewStatus": "needs-human-gameplay-validation",
    "notes": []
  }
}
