{
  "schema": "bloodmoon.knowledge.equipment-item.v1",
  "id": "set-lucky-deruff-s-gru-hill",
  "slug": "deruff-s-gru-hill",
  "name": "Deruff's Gru Hill",
  "title": "Deruff's Gru Hill",
  "category": "Set Lucky",
  "categorySlug": "set-lucky",
  "usableBy": [],
  "listStats": {
    "value1": "Deruff Boots",
    "value2": "Deruff Gloves",
    "value3": "Deruff Helm",
    "value4": "Deruff Pants",
    "value5": "Deruff Armor"
  },
  "image": {
    "publicPath": null,
    "sourceUrl": null,
    "localPath": null,
    "size": null,
    "sha1": null
  },
  "source": {
    "normalizedIndex": "apps/web/data/muEquipmentIndex.generated.json",
    "detailFile": "apps/web/data/mu-equipment-details/set-lucky.json",
    "sourceUrl": "https://www.guiamuonline.com/spanish/items/lucky/deruff.html",
    "imageSourceUrl": null
  },
  "statsByLevel": [
    {
      "itemLevel": 0,
      "defense": 45,
      "durability": null,
      "damageMin": null,
      "damageMax": null,
      "requiredStrength": 0,
      "requiredAgility": 0,
      "excellentDefense": null,
      "excellentRequiredStrength": null,
      "excellentRequiredAgility": null
    },
    {
      "itemLevel": 1,
      "defense": 48,
      "durability": null,
      "damageMin": null,
      "damageMax": null,
      "requiredStrength": 0,
      "requiredAgility": 0,
      "excellentDefense": null,
      "excellentRequiredStrength": null,
      "excellentRequiredAgility": null
    },
    {
      "itemLevel": 2,
      "defense": 51,
      "durability": null,
      "damageMin": null,
      "damageMax": null,
      "requiredStrength": 0,
      "requiredAgility": 0,
      "excellentDefense": null,
      "excellentRequiredStrength": null,
      "excellentRequiredAgility": null
    },
    {
      "itemLevel": 3,
      "defense": 54,
      "durability": null,
      "damageMin": null,
      "damageMax": null,
      "requiredStrength": 0,
      "requiredAgility": 0,
      "excellentDefense": null,
      "excellentRequiredStrength": null,
      "excellentRequiredAgility": null
    },
    {
      "itemLevel": 4,
      "defense": 57,
      "durability": null,
      "damageMin": null,
      "damageMax": null,
      "requiredStrength": 0,
      "requiredAgility": 0,
      "excellentDefense": null,
      "excellentRequiredStrength": null,
      "excellentRequiredAgility": null
    },
    {
      "itemLevel": 5,
      "defense": 60,
      "durability": null,
      "damageMin": null,
      "damageMax": null,
      "requiredStrength": 0,
      "requiredAgility": 0,
      "excellentDefense": null,
      "excellentRequiredStrength": null,
      "excellentRequiredAgility": null
    },
    {
      "itemLevel": 6,
      "defense": 63,
      "durability": null,
      "damageMin": null,
      "damageMax": null,
      "requiredStrength": 0,
      "requiredAgility": 0,
      "excellentDefense": null,
      "excellentRequiredStrength": null,
      "excellentRequiredAgility": null
    },
    {
      "itemLevel": 7,
      "defense": 66,
      "durability": null,
      "damageMin": null,
      "damageMax": null,
      "requiredStrength": 0,
      "requiredAgility": 0,
      "excellentDefense": null,
      "excellentRequiredStrength": null,
      "excellentRequiredAgility": null
    },
    {
      "itemLevel": 8,
      "defense": 69,
      "durability": null,
      "damageMin": null,
      "damageMax": null,
      "requiredStrength": 0,
      "requiredAgility": 0,
      "excellentDefense": null,
      "excellentRequiredStrength": null,
      "excellentRequiredAgility": null
    },
    {
      "itemLevel": 9,
      "defense": 72,
      "durability": null,
      "damageMin": null,
      "damageMax": null,
      "requiredStrength": 0,
      "requiredAgility": 0,
      "excellentDefense": null,
      "excellentRequiredStrength": null,
      "excellentRequiredAgility": null
    },
    {
      "itemLevel": 10,
      "defense": 76,
      "durability": null,
      "damageMin": null,
      "damageMax": null,
      "requiredStrength": 0,
      "requiredAgility": 0,
      "excellentDefense": null,
      "excellentRequiredStrength": null,
      "excellentRequiredAgility": null
    },
    {
      "itemLevel": 11,
      "defense": 81,
      "durability": null,
      "damageMin": null,
      "damageMax": null,
      "requiredStrength": 0,
      "requiredAgility": 0,
      "excellentDefense": null,
      "excellentRequiredStrength": null,
      "excellentRequiredAgility": null
    },
    {
      "itemLevel": 12,
      "defense": 87,
      "durability": null,
      "damageMin": null,
      "damageMax": null,
      "requiredStrength": 0,
      "requiredAgility": 0,
      "excellentDefense": null,
      "excellentRequiredStrength": null,
      "excellentRequiredAgility": null
    },
    {
      "itemLevel": 13,
      "defense": 94,
      "durability": null,
      "damageMin": null,
      "damageMax": null,
      "requiredStrength": 0,
      "requiredAgility": 0,
      "excellentDefense": null,
      "excellentRequiredStrength": null,
      "excellentRequiredAgility": null
    },
    {
      "itemLevel": 14,
      "defense": 102,
      "durability": null,
      "damageMin": null,
      "damageMax": null,
      "requiredStrength": 0,
      "requiredAgility": 0,
      "excellentDefense": null,
      "excellentRequiredStrength": null,
      "excellentRequiredAgility": null
    },
    {
      "itemLevel": 15,
      "defense": 111,
      "durability": null,
      "damageMin": null,
      "damageMax": null,
      "requiredStrength": 0,
      "requiredAgility": 0,
      "excellentDefense": null,
      "excellentRequiredStrength": null,
      "excellentRequiredAgility": null
    }
  ],
  "parts": [
    {
      "name": "Deruff Boots",
      "slug": "deruff-boots",
      "image": {
        "publicPath": "/images/game-assets/guiamuonline/items/original/set-lucky-deruff-s-gru-hill-deruff-boots.jpg",
        "sourceUrl": "https://www.guiamuonline.com/imagenes/items/lucky/Deruff2p.jpg",
        "localPath": "apps/web/public/images/game-assets/guiamuonline/items/original/set-lucky-deruff-s-gru-hill-deruff-boots.jpg",
        "size": 931,
        "sha1": "4279b20753c6c8cea146331e695048f896614b8e"
      },
      "imageError": null,
      "statsByLevel": []
    },
    {
      "name": "Deruff Gloves",
      "slug": "deruff-gloves",
      "image": {
        "publicPath": "/images/game-assets/guiamuonline/items/original/set-lucky-deruff-s-gru-hill-deruff-gloves.jpg",
        "sourceUrl": "https://www.guiamuonline.com/imagenes/items/lucky/Deruff3p.jpg",
        "localPath": "apps/web/public/images/game-assets/guiamuonline/items/original/set-lucky-deruff-s-gru-hill-deruff-gloves.jpg",
        "size": 983,
        "sha1": "2d386d9761205495ba7791b471d9868499de15f3"
      },
      "imageError": null,
      "statsByLevel": []
    },
    {
      "name": "Deruff Helm",
      "slug": "deruff-helm",
      "image": {
        "publicPath": "/images/game-assets/guiamuonline/items/original/set-lucky-deruff-s-gru-hill-deruff-helm.jpg",
        "sourceUrl": "https://www.guiamuonline.com/imagenes/items/lucky/Deruff5p.jpg",
        "localPath": "apps/web/public/images/game-assets/guiamuonline/items/original/set-lucky-deruff-s-gru-hill-deruff-helm.jpg",
        "size": 845,
        "sha1": "4516d74365be38661f147ffcea52ae33cc819e6e"
      },
      "imageError": null,
      "statsByLevel": []
    },
    {
      "name": "Deruff Pants",
      "slug": "deruff-pants",
      "image": {
        "publicPath": "/images/game-assets/guiamuonline/items/original/set-lucky-deruff-s-gru-hill-deruff-pants.jpg",
        "sourceUrl": "https://www.guiamuonline.com/imagenes/items/lucky/Deruff4p.jpg",
        "localPath": "apps/web/public/images/game-assets/guiamuonline/items/original/set-lucky-deruff-s-gru-hill-deruff-pants.jpg",
        "size": 1211,
        "sha1": "930349bf6b30f2992dc40bcec7edc392088f060c"
      },
      "imageError": null,
      "statsByLevel": []
    },
    {
      "name": "Deruff Armor",
      "slug": "deruff-armor",
      "image": {
        "publicPath": "/images/game-assets/guiamuonline/items/original/set-lucky-deruff-s-gru-hill-deruff-armor.jpg",
        "sourceUrl": "https://www.guiamuonline.com/imagenes/items/lucky/Deruff1p.jpg",
        "localPath": "apps/web/public/images/game-assets/guiamuonline/items/original/set-lucky-deruff-s-gru-hill-deruff-armor.jpg",
        "size": 1179,
        "sha1": "bcb3ce6132b671861bc0b27a4e324c0234b86928"
      },
      "imageError": null,
      "statsByLevel": []
    }
  ],
  "detailParts": [
    {
      "name": "Deruff's Boots",
      "slug": "deruff-s-boots",
      "image": {
        "publicPath": "/images/game-assets/guiamuonline/items/original/set-lucky-deruff-s-gru-hill-deruff-s-boots-detail.jpg",
        "sourceUrl": "https://www.guiamuonline.com/imagenes/items/lucky/Deruff2.jpg",
        "localPath": "apps/web/public/images/game-assets/guiamuonline/items/original/set-lucky-deruff-s-gru-hill-deruff-s-boots-detail.jpg",
        "size": 1465,
        "sha1": "7776198d6a89336fb4e78dcd7f5e43372f4efb5b"
      },
      "imageError": null,
      "statsByLevel": [
        {
          "itemLevel": 0,
          "defense": 45,
          "durability": null,
          "damageMin": null,
          "damageMax": null,
          "requiredStrength": 0,
          "requiredAgility": 0,
          "excellentDefense": null,
          "excellentRequiredStrength": null,
          "excellentRequiredAgility": null
        },
        {
          "itemLevel": 1,
          "defense": 48,
          "durability": null,
          "damageMin": null,
          "damageMax": null,
          "requiredStrength": 0,
          "requiredAgility": 0,
          "excellentDefense": null,
          "excellentRequiredStrength": null,
          "excellentRequiredAgility": null
        },
        {
          "itemLevel": 2,
          "defense": 51,
          "durability": null,
          "damageMin": null,
          "damageMax": null,
          "requiredStrength": 0,
          "requiredAgility": 0,
          "excellentDefense": null,
          "excellentRequiredStrength": null,
          "excellentRequiredAgility": null
        },
        {
          "itemLevel": 3,
          "defense": 54,
          "durability": null,
          "damageMin": null,
          "damageMax": null,
          "requiredStrength": 0,
          "requiredAgility": 0,
          "excellentDefense": null,
          "excellentRequiredStrength": null,
          "excellentRequiredAgility": null
        },
        {
          "itemLevel": 4,
          "defense": 57,
          "durability": null,
          "damageMin": null,
          "damageMax": null,
          "requiredStrength": 0,
          "requiredAgility": 0,
          "excellentDefense": null,
          "excellentRequiredStrength": null,
          "excellentRequiredAgility": null
        },
        {
          "itemLevel": 5,
          "defense": 60,
          "durability": null,
          "damageMin": null,
          "damageMax": null,
          "requiredStrength": 0,
          "requiredAgility": 0,
          "excellentDefense": null,
          "excellentRequiredStrength": null,
          "excellentRequiredAgility": null
        },
        {
          "itemLevel": 6,
          "defense": 63,
          "durability": null,
          "damageMin": null,
          "damageMax": null,
          "requiredStrength": 0,
          "requiredAgility": 0,
          "excellentDefense": null,
          "excellentRequiredStrength": null,
          "excellentRequiredAgility": null
        },
        {
          "itemLevel": 7,
          "defense": 66,
          "durability": null,
          "damageMin": null,
          "damageMax": null,
          "requiredStrength": 0,
          "requiredAgility": 0,
          "excellentDefense": null,
          "excellentRequiredStrength": null,
          "excellentRequiredAgility": null
        },
        {
          "itemLevel": 8,
          "defense": 69,
          "durability": null,
          "damageMin": null,
          "damageMax": null,
          "requiredStrength": 0,
          "requiredAgility": 0,
          "excellentDefense": null,
          "excellentRequiredStrength": null,
          "excellentRequiredAgility": null
        },
        {
          "itemLevel": 9,
          "defense": 72,
          "durability": null,
          "damageMin": null,
          "damageMax": null,
          "requiredStrength": 0,
          "requiredAgility": 0,
          "excellentDefense": null,
          "excellentRequiredStrength": null,
          "excellentRequiredAgility": null
        },
        {
          "itemLevel": 10,
          "defense": 76,
          "durability": null,
          "damageMin": null,
          "damageMax": null,
          "requiredStrength": 0,
          "requiredAgility": 0,
          "excellentDefense": null,
          "excellentRequiredStrength": null,
          "excellentRequiredAgility": null
        },
        {
          "itemLevel": 11,
          "defense": 81,
          "durability": null,
          "damageMin": null,
          "damageMax": null,
          "requiredStrength": 0,
          "requiredAgility": 0,
          "excellentDefense": null,
          "excellentRequiredStrength": null,
          "excellentRequiredAgility": null
        },
        {
          "itemLevel": 12,
          "defense": 87,
          "durability": null,
          "damageMin": null,
          "damageMax": null,
          "requiredStrength": 0,
          "requiredAgility": 0,
          "excellentDefense": null,
          "excellentRequiredStrength": null,
          "excellentRequiredAgility": null
        },
        {
          "itemLevel": 13,
          "defense": 94,
          "durability": null,
          "damageMin": null,
          "damageMax": null,
          "requiredStrength": 0,
          "requiredAgility": 0,
          "excellentDefense": null,
          "excellentRequiredStrength": null,
          "excellentRequiredAgility": null
        },
        {
          "itemLevel": 14,
          "defense": 102,
          "durability": null,
          "damageMin": null,
          "damageMax": null,
          "requiredStrength": 0,
          "requiredAgility": 0,
          "excellentDefense": null,
          "excellentRequiredStrength": null,
          "excellentRequiredAgility": null
        },
        {
          "itemLevel": 15,
          "defense": 111,
          "durability": null,
          "damageMin": null,
          "damageMax": null,
          "requiredStrength": 0,
          "requiredAgility": 0,
          "excellentDefense": null,
          "excellentRequiredStrength": null,
          "excellentRequiredAgility": null
        }
      ]
    },
    {
      "name": "Deruff's Gloves",
      "slug": "deruff-s-gloves",
      "image": {
        "publicPath": "/images/game-assets/guiamuonline/items/original/set-lucky-deruff-s-gru-hill-deruff-s-gloves-detail.jpg",
        "sourceUrl": "https://www.guiamuonline.com/imagenes/items/lucky/Deruff3.jpg",
        "localPath": "apps/web/public/images/game-assets/guiamuonline/items/original/set-lucky-deruff-s-gru-hill-deruff-s-gloves-detail.jpg",
        "size": 1475,
        "sha1": "af4e3c7fcf7cdefbfaef37f8b84ee068c9a328c3"
      },
      "imageError": null,
      "statsByLevel": [
        {
          "itemLevel": 0,
          "defense": 42,
          "durability": null,
          "damageMin": null,
          "damageMax": null,
          "requiredStrength": 0,
          "requiredAgility": 0,
          "excellentDefense": null,
          "excellentRequiredStrength": null,
          "excellentRequiredAgility": null
        },
        {
          "itemLevel": 1,
          "defense": 45,
          "durability": null,
          "damageMin": null,
          "damageMax": null,
          "requiredStrength": 0,
          "requiredAgility": 0,
          "excellentDefense": null,
          "excellentRequiredStrength": null,
          "excellentRequiredAgility": null
        },
        {
          "itemLevel": 2,
          "defense": 48,
          "durability": null,
          "damageMin": null,
          "damageMax": null,
          "requiredStrength": 0,
          "requiredAgility": 0,
          "excellentDefense": null,
          "excellentRequiredStrength": null,
          "excellentRequiredAgility": null
        },
        {
          "itemLevel": 3,
          "defense": 51,
          "durability": null,
          "damageMin": null,
          "damageMax": null,
          "requiredStrength": 0,
          "requiredAgility": 0,
          "excellentDefense": null,
          "excellentRequiredStrength": null,
          "excellentRequiredAgility": null
        },
        {
          "itemLevel": 4,
          "defense": 54,
          "durability": null,
          "damageMin": null,
          "damageMax": null,
          "requiredStrength": 0,
          "requiredAgility": 0,
          "excellentDefense": null,
          "excellentRequiredStrength": null,
          "excellentRequiredAgility": null
        },
        {
          "itemLevel": 5,
          "defense": 57,
          "durability": null,
          "damageMin": null,
          "damageMax": null,
          "requiredStrength": 0,
          "requiredAgility": 0,
          "excellentDefense": null,
          "excellentRequiredStrength": null,
          "excellentRequiredAgility": null
        },
        {
          "itemLevel": 6,
          "defense": 60,
          "durability": null,
          "damageMin": null,
          "damageMax": null,
          "requiredStrength": 0,
          "requiredAgility": 0,
          "excellentDefense": null,
          "excellentRequiredStrength": null,
          "excellentRequiredAgility": null
        },
        {
          "itemLevel": 7,
          "defense": 63,
          "durability": null,
          "damageMin": null,
          "damageMax": null,
          "requiredStrength": 0,
          "requiredAgility": 0,
          "excellentDefense": null,
          "excellentRequiredStrength": null,
          "excellentRequiredAgility": null
        },
        {
          "itemLevel": 8,
          "defense": 66,
          "durability": null,
          "damageMin": null,
          "damageMax": null,
          "requiredStrength": 0,
          "requiredAgility": 0,
          "excellentDefense": null,
          "excellentRequiredStrength": null,
          "excellentRequiredAgility": null
        },
        {
          "itemLevel": 9,
          "defense": 69,
          "durability": null,
          "damageMin": null,
          "damageMax": null,
          "requiredStrength": 0,
          "requiredAgility": 0,
          "excellentDefense": null,
          "excellentRequiredStrength": null,
          "excellentRequiredAgility": null
        },
        {
          "itemLevel": 10,
          "defense": 73,
          "durability": null,
          "damageMin": null,
          "damageMax": null,
          "requiredStrength": 0,
          "requiredAgility": 0,
          "excellentDefense": null,
          "excellentRequiredStrength": null,
          "excellentRequiredAgility": null
        },
        {
          "itemLevel": 11,
          "defense": 78,
          "durability": null,
          "damageMin": null,
          "damageMax": null,
          "requiredStrength": 0,
          "requiredAgility": 0,
          "excellentDefense": null,
          "excellentRequiredStrength": null,
          "excellentRequiredAgility": null
        },
        {
          "itemLevel": 12,
          "defense": 84,
          "durability": null,
          "damageMin": null,
          "damageMax": null,
          "requiredStrength": 0,
          "requiredAgility": 0,
          "excellentDefense": null,
          "excellentRequiredStrength": null,
          "excellentRequiredAgility": null
        },
        {
          "itemLevel": 13,
          "defense": 91,
          "durability": null,
          "damageMin": null,
          "damageMax": null,
          "requiredStrength": 0,
          "requiredAgility": 0,
          "excellentDefense": null,
          "excellentRequiredStrength": null,
          "excellentRequiredAgility": null
        },
        {
          "itemLevel": 14,
          "defense": 99,
          "durability": null,
          "damageMin": null,
          "damageMax": null,
          "requiredStrength": 0,
          "requiredAgility": 0,
          "excellentDefense": null,
          "excellentRequiredStrength": null,
          "excellentRequiredAgility": null
        },
        {
          "itemLevel": 15,
          "defense": 108,
          "durability": null,
          "damageMin": null,
          "damageMax": null,
          "requiredStrength": 0,
          "requiredAgility": 0,
          "excellentDefense": null,
          "excellentRequiredStrength": null,
          "excellentRequiredAgility": null
        }
      ]
    },
    {
      "name": "Deruff's Helm",
      "slug": "deruff-s-helm",
      "image": {
        "publicPath": "/images/game-assets/guiamuonline/items/original/set-lucky-deruff-s-gru-hill-deruff-s-helm-detail.jpg",
        "sourceUrl": "https://www.guiamuonline.com/imagenes/items/lucky/Deruff5.jpg",
        "localPath": "apps/web/public/images/game-assets/guiamuonline/items/original/set-lucky-deruff-s-gru-hill-deruff-s-helm-detail.jpg",
        "size": 1270,
        "sha1": "9b49664935d8ea2f746793dacf39ce735f28ba85"
      },
      "imageError": null,
      "statsByLevel": [
        {
          "itemLevel": 0,
          "defense": 50,
          "durability": null,
          "damageMin": null,
          "damageMax": null,
          "requiredStrength": 0,
          "requiredAgility": 0,
          "excellentDefense": null,
          "excellentRequiredStrength": null,
          "excellentRequiredAgility": null
        },
        {
          "itemLevel": 1,
          "defense": 53,
          "durability": null,
          "damageMin": null,
          "damageMax": null,
          "requiredStrength": 0,
          "requiredAgility": 0,
          "excellentDefense": null,
          "excellentRequiredStrength": null,
          "excellentRequiredAgility": null
        },
        {
          "itemLevel": 2,
          "defense": 56,
          "durability": null,
          "damageMin": null,
          "damageMax": null,
          "requiredStrength": 0,
          "requiredAgility": 0,
          "excellentDefense": null,
          "excellentRequiredStrength": null,
          "excellentRequiredAgility": null
        },
        {
          "itemLevel": 3,
          "defense": 59,
          "durability": null,
          "damageMin": null,
          "damageMax": null,
          "requiredStrength": 0,
          "requiredAgility": 0,
          "excellentDefense": null,
          "excellentRequiredStrength": null,
          "excellentRequiredAgility": null
        },
        {
          "itemLevel": 4,
          "defense": 62,
          "durability": null,
          "damageMin": null,
          "damageMax": null,
          "requiredStrength": 0,
          "requiredAgility": 0,
          "excellentDefense": null,
          "excellentRequiredStrength": null,
          "excellentRequiredAgility": null
        },
        {
          "itemLevel": 5,
          "defense": 65,
          "durability": null,
          "damageMin": null,
          "damageMax": null,
          "requiredStrength": 0,
          "requiredAgility": 0,
          "excellentDefense": null,
          "excellentRequiredStrength": null,
          "excellentRequiredAgility": null
        },
        {
          "itemLevel": 6,
          "defense": 68,
          "durability": null,
          "damageMin": null,
          "damageMax": null,
          "requiredStrength": 0,
          "requiredAgility": 0,
          "excellentDefense": null,
          "excellentRequiredStrength": null,
          "excellentRequiredAgility": null
        },
        {
          "itemLevel": 7,
          "defense": 71,
          "durability": null,
          "damageMin": null,
          "damageMax": null,
          "requiredStrength": 0,
          "requiredAgility": 0,
          "excellentDefense": null,
          "excellentRequiredStrength": null,
          "excellentRequiredAgility": null
        },
        {
          "itemLevel": 8,
          "defense": 74,
          "durability": null,
          "damageMin": null,
          "damageMax": null,
          "requiredStrength": 0,
          "requiredAgility": 0,
          "excellentDefense": null,
          "excellentRequiredStrength": null,
          "excellentRequiredAgility": null
        },
        {
          "itemLevel": 9,
          "defense": 77,
          "durability": null,
          "damageMin": null,
          "damageMax": null,
          "requiredStrength": 0,
          "requiredAgility": 0,
          "excellentDefense": null,
          "excellentRequiredStrength": null,
          "excellentRequiredAgility": null
        },
        {
          "itemLevel": 10,
          "defense": 81,
          "durability": null,
          "damageMin": null,
          "damageMax": null,
          "requiredStrength": 0,
          "requiredAgility": 0,
          "excellentDefense": null,
          "excellentRequiredStrength": null,
          "excellentRequiredAgility": null
        },
        {
          "itemLevel": 11,
          "defense": 86,
          "durability": null,
          "damageMin": null,
          "damageMax": null,
          "requiredStrength": 0,
          "requiredAgility": 0,
          "excellentDefense": null,
          "excellentRequiredStrength": null,
          "excellentRequiredAgility": null
        },
        {
          "itemLevel": 12,
          "defense": 92,
          "durability": null,
          "damageMin": null,
          "damageMax": null,
          "requiredStrength": 0,
          "requiredAgility": 0,
          "excellentDefense": null,
          "excellentRequiredStrength": null,
          "excellentRequiredAgility": null
        },
        {
          "itemLevel": 13,
          "defense": 99,
          "durability": null,
          "damageMin": null,
          "damageMax": null,
          "requiredStrength": 0,
          "requiredAgility": 0,
          "excellentDefense": null,
          "excellentRequiredStrength": null,
          "excellentRequiredAgility": null
        },
        {
          "itemLevel": 14,
          "defense": 107,
          "durability": null,
          "damageMin": null,
          "damageMax": null,
          "requiredStrength": 0,
          "requiredAgility": 0,
          "excellentDefense": null,
          "excellentRequiredStrength": null,
          "excellentRequiredAgility": null
        },
        {
          "itemLevel": 15,
          "defense": 116,
          "durability": null,
          "damageMin": null,
          "damageMax": null,
          "requiredStrength": 0,
          "requiredAgility": 0,
          "excellentDefense": null,
          "excellentRequiredStrength": null,
          "excellentRequiredAgility": null
        }
      ]
    },
    {
      "name": "Deruff's Pants",
      "slug": "deruff-s-pants",
      "image": {
        "publicPath": "/images/game-assets/guiamuonline/items/original/set-lucky-deruff-s-gru-hill-deruff-s-pants-detail.jpg",
        "sourceUrl": "https://www.guiamuonline.com/imagenes/items/lucky/Deruff4.jpg",
        "localPath": "apps/web/public/images/game-assets/guiamuonline/items/original/set-lucky-deruff-s-gru-hill-deruff-s-pants-detail.jpg",
        "size": 2276,
        "sha1": "27a2c6e0b222b1b6a2cdfea442efb511f1257be8"
      },
      "imageError": null,
      "statsByLevel": [
        {
          "itemLevel": 0,
          "defense": 54,
          "durability": null,
          "damageMin": null,
          "damageMax": null,
          "requiredStrength": 0,
          "requiredAgility": 0,
          "excellentDefense": null,
          "excellentRequiredStrength": null,
          "excellentRequiredAgility": null
        },
        {
          "itemLevel": 1,
          "defense": 57,
          "durability": null,
          "damageMin": null,
          "damageMax": null,
          "requiredStrength": 0,
          "requiredAgility": 0,
          "excellentDefense": null,
          "excellentRequiredStrength": null,
          "excellentRequiredAgility": null
        },
        {
          "itemLevel": 2,
          "defense": 60,
          "durability": null,
          "damageMin": null,
          "damageMax": null,
          "requiredStrength": 0,
          "requiredAgility": 0,
          "excellentDefense": null,
          "excellentRequiredStrength": null,
          "excellentRequiredAgility": null
        },
        {
          "itemLevel": 3,
          "defense": 63,
          "durability": null,
          "damageMin": null,
          "damageMax": null,
          "requiredStrength": 0,
          "requiredAgility": 0,
          "excellentDefense": null,
          "excellentRequiredStrength": null,
          "excellentRequiredAgility": null
        },
        {
          "itemLevel": 4,
          "defense": 66,
          "durability": null,
          "damageMin": null,
          "damageMax": null,
          "requiredStrength": 0,
          "requiredAgility": 0,
          "excellentDefense": null,
          "excellentRequiredStrength": null,
          "excellentRequiredAgility": null
        },
        {
          "itemLevel": 5,
          "defense": 69,
          "durability": null,
          "damageMin": null,
          "damageMax": null,
          "requiredStrength": 0,
          "requiredAgility": 0,
          "excellentDefense": null,
          "excellentRequiredStrength": null,
          "excellentRequiredAgility": null
        },
        {
          "itemLevel": 6,
          "defense": 72,
          "durability": null,
          "damageMin": null,
          "damageMax": null,
          "requiredStrength": 0,
          "requiredAgility": 0,
          "excellentDefense": null,
          "excellentRequiredStrength": null,
          "excellentRequiredAgility": null
        },
        {
          "itemLevel": 7,
          "defense": 75,
          "durability": null,
          "damageMin": null,
          "damageMax": null,
          "requiredStrength": 0,
          "requiredAgility": 0,
          "excellentDefense": null,
          "excellentRequiredStrength": null,
          "excellentRequiredAgility": null
        },
        {
          "itemLevel": 8,
          "defense": 78,
          "durability": null,
          "damageMin": null,
          "damageMax": null,
          "requiredStrength": 0,
          "requiredAgility": 0,
          "excellentDefense": null,
          "excellentRequiredStrength": null,
          "excellentRequiredAgility": null
        },
        {
          "itemLevel": 9,
          "defense": 81,
          "durability": null,
          "damageMin": null,
          "damageMax": null,
          "requiredStrength": 0,
          "requiredAgility": 0,
          "excellentDefense": null,
          "excellentRequiredStrength": null,
          "excellentRequiredAgility": null
        },
        {
          "itemLevel": 10,
          "defense": 85,
          "durability": null,
          "damageMin": null,
          "damageMax": null,
          "requiredStrength": 0,
          "requiredAgility": 0,
          "excellentDefense": null,
          "excellentRequiredStrength": null,
          "excellentRequiredAgility": null
        },
        {
          "itemLevel": 11,
          "defense": 90,
          "durability": null,
          "damageMin": null,
          "damageMax": null,
          "requiredStrength": 0,
          "requiredAgility": 0,
          "excellentDefense": null,
          "excellentRequiredStrength": null,
          "excellentRequiredAgility": null
        },
        {
          "itemLevel": 12,
          "defense": 96,
          "durability": null,
          "damageMin": null,
          "damageMax": null,
          "requiredStrength": 0,
          "requiredAgility": 0,
          "excellentDefense": null,
          "excellentRequiredStrength": null,
          "excellentRequiredAgility": null
        },
        {
          "itemLevel": 13,
          "defense": 103,
          "durability": null,
          "damageMin": null,
          "damageMax": null,
          "requiredStrength": 0,
          "requiredAgility": 0,
          "excellentDefense": null,
          "excellentRequiredStrength": null,
          "excellentRequiredAgility": null
        },
        {
          "itemLevel": 14,
          "defense": 111,
          "durability": null,
          "damageMin": null,
          "damageMax": null,
          "requiredStrength": 0,
          "requiredAgility": 0,
          "excellentDefense": null,
          "excellentRequiredStrength": null,
          "excellentRequiredAgility": null
        },
        {
          "itemLevel": 15,
          "defense": 120,
          "durability": null,
          "damageMin": null,
          "damageMax": null,
          "requiredStrength": 0,
          "requiredAgility": 0,
          "excellentDefense": null,
          "excellentRequiredStrength": null,
          "excellentRequiredAgility": null
        }
      ]
    },
    {
      "name": "Deruff's Armor",
      "slug": "deruff-s-armor",
      "image": {
        "publicPath": "/images/game-assets/guiamuonline/items/original/set-lucky-deruff-s-gru-hill-deruff-s-armor-detail.jpg",
        "sourceUrl": "https://www.guiamuonline.com/imagenes/items/lucky/Deruff1.jpg",
        "localPath": "apps/web/public/images/game-assets/guiamuonline/items/original/set-lucky-deruff-s-gru-hill-deruff-s-armor-detail.jpg",
        "size": 2148,
        "sha1": "80f8e45318083c46c810ae1ead239da231c65b93"
      },
      "imageError": null,
      "statsByLevel": [
        {
          "itemLevel": 0,
          "defense": 60,
          "durability": null,
          "damageMin": null,
          "damageMax": null,
          "requiredStrength": 0,
          "requiredAgility": 0,
          "excellentDefense": null,
          "excellentRequiredStrength": null,
          "excellentRequiredAgility": null
        },
        {
          "itemLevel": 1,
          "defense": 63,
          "durability": null,
          "damageMin": null,
          "damageMax": null,
          "requiredStrength": 0,
          "requiredAgility": 0,
          "excellentDefense": null,
          "excellentRequiredStrength": null,
          "excellentRequiredAgility": null
        },
        {
          "itemLevel": 2,
          "defense": 66,
          "durability": null,
          "damageMin": null,
          "damageMax": null,
          "requiredStrength": 0,
          "requiredAgility": 0,
          "excellentDefense": null,
          "excellentRequiredStrength": null,
          "excellentRequiredAgility": null
        },
        {
          "itemLevel": 3,
          "defense": 69,
          "durability": null,
          "damageMin": null,
          "damageMax": null,
          "requiredStrength": 0,
          "requiredAgility": 0,
          "excellentDefense": null,
          "excellentRequiredStrength": null,
          "excellentRequiredAgility": null
        },
        {
          "itemLevel": 4,
          "defense": 72,
          "durability": null,
          "damageMin": null,
          "damageMax": null,
          "requiredStrength": 0,
          "requiredAgility": 0,
          "excellentDefense": null,
          "excellentRequiredStrength": null,
          "excellentRequiredAgility": null
        },
        {
          "itemLevel": 5,
          "defense": 75,
          "durability": null,
          "damageMin": null,
          "damageMax": null,
          "requiredStrength": 0,
          "requiredAgility": 0,
          "excellentDefense": null,
          "excellentRequiredStrength": null,
          "excellentRequiredAgility": null
        },
        {
          "itemLevel": 6,
          "defense": 78,
          "durability": null,
          "damageMin": null,
          "damageMax": null,
          "requiredStrength": 0,
          "requiredAgility": 0,
          "excellentDefense": null,
          "excellentRequiredStrength": null,
          "excellentRequiredAgility": null
        },
        {
          "itemLevel": 7,
          "defense": 81,
          "durability": null,
          "damageMin": null,
          "damageMax": null,
          "requiredStrength": 0,
          "requiredAgility": 0,
          "excellentDefense": null,
          "excellentRequiredStrength": null,
          "excellentRequiredAgility": null
        },
        {
          "itemLevel": 8,
          "defense": 84,
          "durability": null,
          "damageMin": null,
          "damageMax": null,
          "requiredStrength": 0,
          "requiredAgility": 0,
          "excellentDefense": null,
          "excellentRequiredStrength": null,
          "excellentRequiredAgility": null
        },
        {
          "itemLevel": 9,
          "defense": 87,
          "durability": null,
          "damageMin": null,
          "damageMax": null,
          "requiredStrength": 0,
          "requiredAgility": 0,
          "excellentDefense": null,
          "excellentRequiredStrength": null,
          "excellentRequiredAgility": null
        },
        {
          "itemLevel": 10,
          "defense": 91,
          "durability": null,
          "damageMin": null,
          "damageMax": null,
          "requiredStrength": 0,
          "requiredAgility": 0,
          "excellentDefense": null,
          "excellentRequiredStrength": null,
          "excellentRequiredAgility": null
        },
        {
          "itemLevel": 11,
          "defense": 96,
          "durability": null,
          "damageMin": null,
          "damageMax": null,
          "requiredStrength": 0,
          "requiredAgility": 0,
          "excellentDefense": null,
          "excellentRequiredStrength": null,
          "excellentRequiredAgility": null
        },
        {
          "itemLevel": 12,
          "defense": 102,
          "durability": null,
          "damageMin": null,
          "damageMax": null,
          "requiredStrength": 0,
          "requiredAgility": 0,
          "excellentDefense": null,
          "excellentRequiredStrength": null,
          "excellentRequiredAgility": null
        },
        {
          "itemLevel": 13,
          "defense": 109,
          "durability": null,
          "damageMin": null,
          "damageMax": null,
          "requiredStrength": 0,
          "requiredAgility": 0,
          "excellentDefense": null,
          "excellentRequiredStrength": null,
          "excellentRequiredAgility": null
        },
        {
          "itemLevel": 14,
          "defense": 117,
          "durability": null,
          "damageMin": null,
          "damageMax": null,
          "requiredStrength": 0,
          "requiredAgility": 0,
          "excellentDefense": null,
          "excellentRequiredStrength": null,
          "excellentRequiredAgility": null
        },
        {
          "itemLevel": 15,
          "defense": 126,
          "durability": null,
          "damageMin": null,
          "damageMax": null,
          "requiredStrength": 0,
          "requiredAgility": 0,
          "excellentDefense": null,
          "excellentRequiredStrength": null,
          "excellentRequiredAgility": null
        }
      ]
    }
  ],
  "editorial": {
    "status": "cataloged-from-normalized-source",
    "reviewStatus": "needs-human-gameplay-validation",
    "notes": []
  }
}
